LICENSE.txt
MANIFEST.in
README.rst
dev_requirements.txt
requirements.txt
setup.py
graffiti_monkey/__init__.py
graffiti_monkey/cache.py
graffiti_monkey/cli.py
graffiti_monkey/core.py
graffiti_monkey/exceptions.py
graffiti_monkey.egg-info/PKG-INFO
graffiti_monkey.egg-info/SOURCES.txt
graffiti_monkey.egg-info/dependency_links.txt
graffiti_monkey.egg-info/entry_points.txt
graffiti_monkey.egg-info/not-zip-safe
graffiti_monkey.egg-info/requires.txt
graffiti_monkey.egg-info/top_level.txt