Metadata-Version: 1.1
Name: graffiti-monkey
Version: 0.6.0
Summary: A service that propagates tags from EC2 instances to EBS Volumes, and then to EBS Snapshots
Home-page: https://github.com/Answers4AWS/graffiti-monkey
Author: Peter Sankauskas
Author-email: info@answersforaws.com
License: Apache License
